pyMultiOmics/__init__.py
pyMultiOmics/analysis.py
pyMultiOmics/base.py
pyMultiOmics/common.py
pyMultiOmics/constants.py
pyMultiOmics/functions.py
pyMultiOmics/harmonizomeapi.py
pyMultiOmics/info.py
pyMultiOmics/mapping.py
pyMultiOmics/metadata.py
pyMultiOmics/mofax.py
pyMultiOmics/pipelines.py
pyMultiOmics/plots.py
pyMultiOmics/query.py
pyMultiOmics/reactome.py
pyMultiOmics/data/chebi_bfs_relation_dict.pkl
pyMultiOmics/data/compound_names.p
pyMultiOmics/data/gene_names.p
pyMultiOmics/data/go_data.p
pyMultiOmics/data/kegg_to_chebi.p
pyMultiOmics/data/relation.tsv
pyMultiOmics-1.0.4.dist-info/LICENSE
pyMultiOmics-1.0.4.dist-info/METADATA
pyMultiOmics-1.0.4.dist-info/WHEEL
pyMultiOmics-1.0.4.dist-info/top_level.txt
pyMultiOmics-1.0.4.dist-info/RECORD
