Metadata-Version: 2.1
Name: pyMultiOmics
Version: 1.0.4
Summary: A Python package for multi-omics data integration and analysis
Home-page: https://github.com/glasgowcompbio/pyMultiOmics
Author: Joe Wandy
Author-email: joe.wandy@glasgow.ac.uk
License: UNKNOWN
Platform: UNKNOWN
Classifier: Programming Language :: Python :: 3
Classifier: License :: OSI Approved :: MIT License
Classifier: Operating System :: OS Independent
Requires-Python: >=3.6
License-File: LICENSE
Requires-Dist: numpy
Requires-Dist: scipy
Requires-Dist: pandas
Requires-Dist: seaborn
Requires-Dist: scikit-learn
Requires-Dist: matplotlib
Requires-Dist: plotly
Requires-Dist: statsmodels
Requires-Dist: loguru
Requires-Dist: requests
Requires-Dist: neo4j-driver
Requires-Dist: tqdm
Requires-Dist: pillow
Requires-Dist: jupyterlab
Requires-Dist: bioservices
Requires-Dist: networkx
Requires-Dist: tzlocal
Requires-Dist: pals-pathway
Requires-Dist: mofapy2
Requires-Dist: mofax
